offspring/__init__.py
offspring/process.py
offspring-0.0.3.dist-info/DESCRIPTION.rst
offspring-0.0.3.dist-info/METADATA
offspring-0.0.3.dist-info/RECORD
offspring-0.0.3.dist-info/WHEEL
offspring-0.0.3.dist-info/metadata.json
offspring-0.0.3.dist-info/top_level.txt
