Metadata-Version: 2.0
Name: offspring
Version: 0.0.3
Summary: Objects and patterns for working with processes in Python using the multiprocessing library
Home-page: https://github.com/borgstrom/offspring
Author: Evan Borgstrom
Author-email: evan.borgstrom@gmail.com
License: Apache 2
Platform: UNKNOWN
